fmpy/__init__.py
fmpy/__main__.py
fmpy/build.py
fmpy/cli.py
fmpy/fmi1.py
fmpy/fmi2.py
fmpy/fmi3.py
fmpy/model_description.py
fmpy/simulation.py
fmpy/template.py
fmpy/util.py
fmpy/validation.py
fmpy/c-code/CMakeLists.txt
fmpy/c-code/fmi1Functions.h
fmpy/c-code/fmi2FunctionTypes.h
fmpy/c-code/fmi2Functions.h
fmpy/c-code/fmi2TypesPlatform.h
fmpy/c-code/fmi3FunctionTypes.h
fmpy/c-code/fmi3Functions.h
fmpy/c-code/fmi3PlatformTypes.h
fmpy/cross_check/__init__.py
fmpy/cross_check/__main__.py
fmpy/cross_check/cross_check.py
fmpy/cross_check/result_tables.py
fmpy/cross_check/validate_vendor_repo.py
fmpy/cswrapper/__init__.py
fmpy/cswrapper/license.txt
fmpy/examples/__init__.py
fmpy/examples/continue_simulation.py
fmpy/examples/coupled_clutches.py
fmpy/examples/custom_input.py
fmpy/examples/efficient_loops.py
fmpy/examples/parameter_variation.py
fmpy/fmucontainer/__init__.py
fmpy/fmucontainer/documentation/LICENSE.txt
fmpy/fmucontainer/sources/FMI.c
fmpy/fmucontainer/sources/FMI.h
fmpy/fmucontainer/sources/FMI2.c
fmpy/fmucontainer/sources/FMI2.h
fmpy/fmucontainer/sources/FMUContainer.c
fmpy/fmucontainer/sources/FMUContainer.h
fmpy/fmucontainer/sources/buildDescription.xml
fmpy/fmucontainer/sources/fmi2Functions.c
fmpy/fmucontainer/sources/fmi3Functions.c
fmpy/fmucontainer/sources/mpack-common.c
fmpy/fmucontainer/sources/mpack-common.h
fmpy/fmucontainer/sources/mpack-expect.c
fmpy/fmucontainer/sources/mpack-expect.h
fmpy/fmucontainer/sources/mpack-node.c
fmpy/fmucontainer/sources/mpack-node.h
fmpy/fmucontainer/sources/mpack-platform.c
fmpy/fmucontainer/sources/mpack-platform.h
fmpy/fmucontainer/sources/mpack-reader.c
fmpy/fmucontainer/sources/mpack-reader.h
fmpy/fmucontainer/sources/mpack-writer.c
fmpy/fmucontainer/sources/mpack-writer.h
fmpy/fmucontainer/sources/mpack.h
fmpy/fmucontainer/templates/FMI2.xml
fmpy/fmucontainer/templates/FMI3.xml
fmpy/gui/BuildDialog.py
fmpy/gui/BuildThread.py
fmpy/gui/MainWindow.py
fmpy/gui/NewFMUDialog.py
fmpy/gui/TableDialog.py
fmpy-0.3.27.dist-info/METADATA
fmpy-0.3.27.dist-info/WHEEL
fmpy-0.3.27.dist-info/entry_points.txt
fmpy-0.3.27.dist-info/licenses/LICENSE.txt
fmpy-0.3.27.dist-info/RECORD
