Metadata-Version: 2.4
Name: FMPy
Version: 0.3.27
Summary: Simulate Functional Mock-up Units (FMUs) in Python
License-File: LICENSE.txt
Requires-Python: >=3.10
Requires-Dist: attrs>=24.2.0
Requires-Dist: cmake>=4.0.3
Requires-Dist: jinja2>=3.1.4
Requires-Dist: lark>=1.2.2
Requires-Dist: lxml>=5.3.0
Requires-Dist: msgpack>=1.1.0
Requires-Dist: nbformat>=5.10.4
Requires-Dist: numpy>=2.1.3
Provides-Extra: complete
Requires-Dist: dash-bootstrap-components>=2.0.1; extra == 'complete'
Requires-Dist: dask[bag]>=2024.11.2; extra == 'complete'
Requires-Dist: plotly>=5.24.1; extra == 'complete'
Requires-Dist: pyqtgraph>=0.13.7; extra == 'complete'
Requires-Dist: pyside6>=6.8.0.2; extra == 'complete'
Requires-Dist: pywin32>=308; (sys_platform == 'win32') and extra == 'complete'
Requires-Dist: requests>=2.32.3; extra == 'complete'
Requires-Dist: scipy>=1.14.1; extra == 'complete'
Provides-Extra: examples
Requires-Dist: dask[bag]>=2024.11.2; extra == 'examples'
Requires-Dist: requests>=2.32.3; extra == 'examples'
Provides-Extra: gui
Requires-Dist: pyqtgraph>=0.13.7; extra == 'gui'
Requires-Dist: pyside6>=6.8.0.2; extra == 'gui'
Requires-Dist: pywin32>=308; (sys_platform == 'win32') and extra == 'gui'
Provides-Extra: plot
Requires-Dist: plotly>=5.24.1; extra == 'plot'
Requires-Dist: scipy>=1.14.1; extra == 'plot'
Provides-Extra: webapp
Requires-Dist: dash-bootstrap-components>=2.0.1; extra == 'webapp'
